pityu/__init__.py
pityu/main.py
pityu-1.0.dist-info/METADATA
pityu-1.0.dist-info/WHEEL
pityu-1.0.dist-info/top_level.txt
pityu-1.0.dist-info/RECORD
