Metadata-Version: 2.1
Name: pityu
Version: 1.0
Summary: A description of your package
Author: Pityu
Author-email: pista1125@gmail.com
License: MIT
